lib389/__init__.py
lib389/_constants.py
lib389/_controls.py
lib389/_entry.py
lib389/_ldifconn.py
lib389/_mapped_object.py
lib389/_mapped_object_lint.py
lib389/_replication.py
lib389/aci.py
lib389/agreement.py
lib389/backend.py
lib389/chaining.py
lib389/config.py
lib389/conflicts.py
lib389/cos.py
lib389/dbgen.py
lib389/dirsrv_log.py
lib389/ds_instance.py
lib389/dseldif.py
lib389/encrypted_attributes.py
lib389/exceptions.py
lib389/extended_operations.py
lib389/extensibleobject.py
lib389/index.py
lib389/ldap_objs.py
lib389/ldapi.py
lib389/ldclt.py
lib389/lint.py
lib389/mappingTree.py
lib389/mit_krb5.py
lib389/monitor.py
lib389/nss_ssl.py
lib389/passwd.py
lib389/password_plugins.py
lib389/paths.py
lib389/perftools.py
lib389/plugins.py
lib389/properties.py
lib389/pwpolicy.py
lib389/referral.py
lib389/replica.py
lib389/repltools.py
lib389/rewriters.py
lib389/rootdse.py
lib389/sasl.py
lib389/saslmap.py
lib389/schema.py
lib389/suffix.py
lib389/tasks.py
lib389/tombstone.py
lib389/tools.py
lib389/topologies.py
lib389/tunables.py
lib389/utils.py
lib389/__pycache__/__init__.cpython-313.pyc
lib389/__pycache__/_constants.cpython-313.pyc
lib389/__pycache__/_controls.cpython-313.pyc
lib389/__pycache__/_entry.cpython-313.pyc
lib389/__pycache__/_ldifconn.cpython-313.pyc
lib389/__pycache__/_mapped_object.cpython-313.pyc
lib389/__pycache__/_mapped_object_lint.cpython-313.pyc
lib389/__pycache__/agreement.cpython-313.pyc
lib389/__pycache__/backend.cpython-313.pyc
lib389/__pycache__/chaining.cpython-313.pyc
lib389/__pycache__/config.cpython-313.pyc
lib389/__pycache__/conflicts.cpython-313.pyc
lib389/__pycache__/cos.cpython-313.pyc
lib389/__pycache__/dbgen.cpython-313.pyc
lib389/__pycache__/dirsrv_log.cpython-313.pyc
lib389/__pycache__/dseldif.cpython-313.pyc
lib389/__pycache__/encrypted_attributes.cpython-313.pyc
lib389/__pycache__/exceptions.cpython-313.pyc
lib389/__pycache__/extended_operations.cpython-313.pyc
lib389/__pycache__/index.cpython-313.pyc
lib389-3.2.0.dist-info/licenses/LICENSE
lib389-3.2.0.dist-info/METADATA
lib389-3.2.0.dist-info/WHEEL
lib389-3.2.0.dist-info/top_level.txt
lib389-3.2.0.dist-info/RECORD
