Metadata-Version: 2.4
Name: lib389
Version: 3.2.0
Summary: A library for accessing, testing, and configuring the 389 Directory Server
Author-email: "Red Hat, Inc., and William Brown" <389-devel@lists.fedoraproject.org>
License: GPL-3.0-or-later
Project-URL: Homepage, https://www.port389.org/docs/389ds/FAQ/upstream-test-framework.html
Project-URL: Documentation, https://www.port389.org/docs/389ds/documentation.html
Project-URL: Repository, https://github.com/389ds/389-ds-base
Project-URL: Issues, https://github.com/389ds/389-ds-base/issues
Keywords: 389,directory,server,test,configure
Classifier: Development Status :: 5 - Production/Stable
Classifier: Intended Audience :: Developers
Classifier: Intended Audience :: System Administrators
Classifier: Operating System :: POSIX :: Linux
Classifier: Programming Language :: Python :: 3
Classifier: Programming Language :: Python :: 3.8
Classifier: Programming Language :: Python :: 3.9
Classifier: Programming Language :: Python :: 3.10
Classifier: Programming Language :: Python :: 3.11
Classifier: Programming Language :: Python :: 3.12
Classifier: Topic :: Software Development :: Libraries :: Python Modules
Classifier: Topic :: Software Development :: Quality Assurance
Classifier: Topic :: Software Development :: Testing
Classifier: Topic :: System :: Systems Administration :: Authentication/Directory :: LDAP
Requires-Python: >=3.8
License-File: LICENSE
Requires-Dist: pyasn1
Requires-Dist: pyasn1-modules
Requires-Dist: python-dateutil
Requires-Dist: argcomplete
Requires-Dist: python-ldap
Requires-Dist: distro
Requires-Dist: cryptography
Requires-Dist: psutil
Dynamic: license-file
